{
  "finances": [
    {
      "name": "side job",
      "amount": 400,
      "date": "2020-06-11",
      "userId": 1,
      "billOrNot": false,
      "totalFinanceId": 1,
      "id": 1
    },
    {
      "name": "credit card bill #1",
      "amount": -122.73,
      "date": "2020-06-15",
      "userId": 1,
      "billOrNot": true,
      "totalFinanceId": 1,
      "id": 2
    }
  ],
  "users": [
    {
      "id": 1,
      "email": "rolankford@gmail.com",
      "password": "1234"
    },
    {
      "id": 23,
      "email": "rol@gmail.com",
      "password": "word"
    }
  ],
  "totalFinances": [
    {
      "month": "June",
      "year": "2020",
      "userId": 1,
      "allIncome": 400,
      "allBills": -122.73,
      "amountLeft": 277.27,
      "id": 1
    }
  ]
}